{"lastUsed":1642669205878,"path":"C:\/myJSP","projectCount":2,"recentFiles":[{"path":"\/basicJSP\/src\/main\/webapp\/response","parentWorkspace":"C:\/myJSP","name":"res_ex01.jsp","lastModified":1642639882287,"locationURI":"file:\/C:\/myJSP\/basicJSP\/src\/main\/webapp\/response\/res_ex01.jsp"},{"path":"\/basicJSP\/src\/main\/webapp\/path","parentWorkspace":"C:\/myJSP","name":"path_ex02.jsp","lastModified":1642580901282,"locationURI":"file:\/C:\/myJSP\/basicJSP\/src\/main\/webapp\/path\/path_ex02.jsp"},{"path":"\/basicJSP\/src\/main\/webapp\/test","parentWorkspace":"C:\/myJSP","name":"scriptlet2.jsp","lastModified":1642477314417,"locationURI":"file:\/C:\/myJSP\/basicJSP\/src\/main\/webapp\/test\/scriptlet2.jsp"},{"path":"\/basicJSP\/src\/main\/webapp\/request","parentWorkspace":"C:\/myJSP","name":"req_get.jsp","lastModified":1642557138610,"locationURI":"file:\/C:\/myJSP\/basicJSP\/src\/main\/webapp\/request\/req_get.jsp"},{"path":"\/basicJSP\/src\/main\/webapp\/test","parentWorkspace":"C:\/myJSP","name":"tag_ex03.jsp","lastModified":1642492176633,"locationURI":"file:\/C:\/myJSP\/basicJSP\/src\/main\/webapp\/test\/tag_ex03.jsp"},{"path":"\/basicJSP\/src\/main\/webapp\/session","parentWorkspace":"C:\/myJSP","name":"session_get.jsp","lastModified":1642669243246,"locationURI":"file:\/C:\/myJSP\/basicJSP\/src\/main\/webapp\/session\/session_get.jsp"},{"path":"\/basicJSP\/src\/main\/webapp\/request","parentWorkspace":"C:\/myJSP","name":"req_basic.jsp","lastModified":1642563127575,"locationURI":"file:\/C:\/myJSP\/basicJSP\/src\/main\/webapp\/request\/req_basic.jsp"},{"path":"\/basicJSP\/src\/main\/webapp\/request","parentWorkspace":"C:\/myJSP","name":"req_quiz01.jsp","lastModified":1642572849679,"locationURI":"file:\/C:\/myJSP\/basicJSP\/src\/main\/webapp\/request\/req_quiz01.jsp"},{"path":"\/basicJSP\/src\/main\/webapp\/request","parentWorkspace":"C:\/myJSP","name":"req_quiz02_ok.jsp","lastModified":1642575081592,"locationURI":"file:\/C:\/myJSP\/basicJSP\/src\/main\/webapp\/request\/req_quiz02_ok.jsp"},{"path":"\/basicJSP\/src\/main\/webapp\/response","parentWorkspace":"C:\/myJSP","name":"login_welcome.jsp","lastModified":1642644599802,"locationURI":"file:\/C:\/myJSP\/basicJSP\/src\/main\/webapp\/response\/login_welcome.jsp"},{"path":"\/basicJSP\/src\/main\/java\/kr\/co\/koo","parentWorkspace":"C:\/myJSP","name":"ServletBasic.java","lastModified":1642496108630,"locationURI":"file:\/C:\/myJSP\/basicJSP\/src\/main\/java\/kr\/co\/koo\/ServletBasic.java"},{"path":"\/basicJSP\/src\/main\/webapp\/response","parentWorkspace":"C:\/myJSP","name":"res_ex01_ok.jsp","lastModified":1642640104992,"locationURI":"file:\/C:\/myJSP\/basicJSP\/src\/main\/webapp\/response\/res_ex01_ok.jsp"},{"path":"\/HTML\/src\/main\/webapp","parentWorkspace":"C:\/myJSP","name":"inline_block.html","lastModified":1642468214278,"locationURI":"file:\/C:\/myJSP\/HTML\/src\/main\/webapp\/inline_block.html"},{"path":"\/basicJSP\/src\/main\/webapp\/cookie","parentWorkspace":"C:\/myJSP","name":"cookie_login_ok.jsp","lastModified":1642663319953,"locationURI":"file:\/C:\/myJSP\/basicJSP\/src\/main\/webapp\/cookie\/cookie_login_ok.jsp"},{"path":"\/basicJSP\/src\/main\/java\/com\/servlet","parentWorkspace":"C:\/myJSP","name":"OutServlet.java","lastModified":1642646965003,"locationURI":"file:\/C:\/myJSP\/basicJSP\/src\/main\/java\/com\/servlet\/OutServlet.java"},{"path":"\/basicJSP\/src\/main\/webapp\/test","parentWorkspace":"C:\/myJSP","name":"testServlet.jsp","lastModified":1642553834898,"locationURI":"file:\/C:\/myJSP\/basicJSP\/src\/main\/webapp\/test\/testServlet.jsp"},{"path":"\/basicJSP\/src\/main\/webapp\/cookie","parentWorkspace":"C:\/myJSP","name":"cookie01.jsp","lastModified":1642656741555,"locationURI":"file:\/C:\/myJSP\/basicJSP\/src\/main\/webapp\/cookie\/cookie01.jsp"},{"path":"\/HTML\/src\/main\/webapp","parentWorkspace":"C:\/myJSP","name":"table.html","lastModified":1642467378634,"locationURI":"file:\/C:\/myJSP\/HTML\/src\/main\/webapp\/table.html"},{"path":"\/basicJSP\/src\/main\/webapp\/request","parentWorkspace":"C:\/myJSP","name":"req_post_form.jsp","lastModified":1642569395033,"locationURI":"file:\/C:\/myJSP\/basicJSP\/src\/main\/webapp\/request\/req_post_form.jsp"},{"path":"\/Servers\/Tomcat v9.0 Server at localhost-config","parentWorkspace":"C:\/myJSP","name":"context.xml","lastModified":1642404120596,"locationURI":"file:\/C:\/myJSP\/Servers\/Tomcat%20v9.0%20Server%20at%20localhost-config\/context.xml"},{"path":"\/basicJSP\/src\/main\/java\/com\/servlet","parentWorkspace":"C:\/myJSP","name":"TestServlet.java","lastModified":1642495241882,"locationURI":"file:\/C:\/myJSP\/basicJSP\/src\/main\/java\/com\/servlet\/TestServlet.java"},{"path":"\/basicJSP\/src\/main\/webapp\/path","parentWorkspace":"C:\/myJSP","name":"path_ex01.jsp","lastModified":1642581029039,"locationURI":"file:\/C:\/myJSP\/basicJSP\/src\/main\/webapp\/path\/path_ex01.jsp"},{"path":"\/basicJSP\/src\/main\/webapp\/test","parentWorkspace":"C:\/myJSP","name":"header.jsp","lastModified":1642484682147,"locationURI":"file:\/C:\/myJSP\/basicJSP\/src\/main\/webapp\/test\/header.jsp"},{"path":"\/basicJSP\/src\/main\/webapp\/path\/test","parentWorkspace":"C:\/myJSP","name":"path_ex03.jsp","lastModified":1642581018925,"locationURI":"file:\/C:\/myJSP\/basicJSP\/src\/main\/webapp\/path\/test\/path_ex03.jsp"},{"path":"\/basicJSP\/src\/main\/webapp\/test","parentWorkspace":"C:\/myJSP","name":"comments.jsp","lastModified":1642478923318,"locationURI":"file:\/C:\/myJSP\/basicJSP\/src\/main\/webapp\/test\/comments.jsp"},{"path":"\/HTML\/src\/main\/webapp","parentWorkspace":"C:\/myJSP","name":"First.html","lastModified":1642408824379,"locationURI":"file:\/C:\/myJSP\/HTML\/src\/main\/webapp\/First.html"},{"path":"\/basicJSP\/src\/main\/webapp\/test","parentWorkspace":"C:\/myJSP","name":"scriptlet.jsp","lastModified":1642474269055,"locationURI":"file:\/C:\/myJSP\/basicJSP\/src\/main\/webapp\/test\/scriptlet.jsp"},{"path":"\/basicJSP\/src\/main\/webapp\/test","parentWorkspace":"C:\/myJSP","name":"directive.jsp","lastModified":1642484541599,"locationURI":"file:\/C:\/myJSP\/basicJSP\/src\/main\/webapp\/test\/directive.jsp"},{"path":"\/basicJSP\/src\/main\/webapp\/response","parentWorkspace":"C:\/myJSP","name":"login_id_fail.jsp","lastModified":1642644401062,"locationURI":"file:\/C:\/myJSP\/basicJSP\/src\/main\/webapp\/response\/login_id_fail.jsp"},{"path":"\/basicJSP\/src\/main\/webapp\/cookie","parentWorkspace":"C:\/myJSP","name":"cookie_set.jsp","lastModified":1642650300549,"locationURI":"file:\/C:\/myJSP\/basicJSP\/src\/main\/webapp\/cookie\/cookie_set.jsp"},{"path":"\/basicJSP\/src\/main\/webapp\/test","parentWorkspace":"C:\/myJSP","name":"testJSP.jsp","lastModified":1642495407423,"locationURI":"file:\/C:\/myJSP\/basicJSP\/src\/main\/webapp\/test\/testJSP.jsp"},{"path":"\/basicJSP\/src\/main\/webapp\/response","parentWorkspace":"C:\/myJSP","name":"login_pw_fail.jsp","lastModified":1642644426675,"locationURI":"file:\/C:\/myJSP\/basicJSP\/src\/main\/webapp\/response\/login_pw_fail.jsp"},{"path":"\/basicJSP\/src\/main\/webapp\/path\/test","parentWorkspace":"C:\/myJSP","name":"path_quiz.jsp","lastModified":1642582771263,"locationURI":"file:\/C:\/myJSP\/basicJSP\/src\/main\/webapp\/path\/test\/path_quiz.jsp"},{"path":"\/basicJSP\/src\/main\/webapp\/response","parentWorkspace":"C:\/myJSP","name":"res_ex01_no.jsp","lastModified":1642640587854,"locationURI":"file:\/C:\/myJSP\/basicJSP\/src\/main\/webapp\/response\/res_ex01_no.jsp"},{"path":"\/HTML\/src\/main\/webapp","parentWorkspace":"C:\/myJSP","name":"image.html","lastModified":1642409676242,"locationURI":"file:\/C:\/myJSP\/HTML\/src\/main\/webapp\/image.html"},{"path":"\/basicJSP\/src\/main\/webapp\/cookie","parentWorkspace":"C:\/myJSP","name":"cookie_get.jsp","lastModified":1642651282755,"locationURI":"file:\/C:\/myJSP\/basicJSP\/src\/main\/webapp\/cookie\/cookie_get.jsp"},{"path":"\/basicJSP\/src\/main\/webapp\/cookie","parentWorkspace":"C:\/myJSP","name":"cookie_welcome.jsp","lastModified":1642668365010,"locationURI":"file:\/C:\/myJSP\/basicJSP\/src\/main\/webapp\/cookie\/cookie_welcome.jsp"},{"path":"\/basicJSP\/src\/main\/webapp\/response","parentWorkspace":"C:\/myJSP","name":"res_ex01_result.jsp","lastModified":1642640400529,"locationURI":"file:\/C:\/myJSP\/basicJSP\/src\/main\/webapp\/response\/res_ex01_result.jsp"},{"path":"\/basicJSP\/src\/main\/webapp\/out","parentWorkspace":"C:\/myJSP","name":"out_ex01.jsp","lastModified":1642646114264,"locationURI":"file:\/C:\/myJSP\/basicJSP\/src\/main\/webapp\/out\/out_ex01.jsp"},{"path":"\/basicJSP\/src\/main\/webapp\/test","parentWorkspace":"C:\/myJSP","name":"tag_ex02.jsp","lastModified":1642489162167,"locationURI":"file:\/C:\/myJSP\/basicJSP\/src\/main\/webapp\/test\/tag_ex02.jsp"},{"path":"\/HTML\/src\/main\/webapp","parentWorkspace":"C:\/myJSP","name":"form.html","lastModified":1642471853579,"locationURI":"file:\/C:\/myJSP\/HTML\/src\/main\/webapp\/form.html"},{"path":"\/basicJSP\/src\/main\/webapp\/request","parentWorkspace":"C:\/myJSP","name":"req_video_ok.jsp","lastModified":1642578867260,"locationURI":"file:\/C:\/myJSP\/basicJSP\/src\/main\/webapp\/request\/req_video_ok.jsp"},{"path":"\/basicJSP\/src\/main\/webapp\/cookie","parentWorkspace":"C:\/myJSP","name":"cookie_login.jsp","lastModified":1642663797594,"locationURI":"file:\/C:\/myJSP\/basicJSP\/src\/main\/webapp\/cookie\/cookie_login.jsp"},{"path":"\/basicJSP\/src\/main\/webapp\/test","parentWorkspace":"C:\/myJSP","name":"declaration.jsp","lastModified":1642478041772,"locationURI":"file:\/C:\/myJSP\/basicJSP\/src\/main\/webapp\/test\/declaration.jsp"},{"path":"\/basicJSP\/src\/main\/webapp\/request","parentWorkspace":"C:\/myJSP","name":"req_quiz02.jsp","lastModified":1642574985027,"locationURI":"file:\/C:\/myJSP\/basicJSP\/src\/main\/webapp\/request\/req_quiz02.jsp"},{"path":"\/basicJSP\/src\/main\/webapp\/request","parentWorkspace":"C:\/myJSP","name":"req_post_parameter.jsp","lastModified":1642569413854,"locationURI":"file:\/C:\/myJSP\/basicJSP\/src\/main\/webapp\/request\/req_post_parameter.jsp"},{"path":"\/basicJSP\/src\/main\/webapp\/request","parentWorkspace":"C:\/myJSP","name":"req_video.jsp","lastModified":1642578913246,"locationURI":"file:\/C:\/myJSP\/basicJSP\/src\/main\/webapp\/request\/req_video.jsp"},{"path":"\/basicJSP\/src\/main\/webapp\/cookie","parentWorkspace":"C:\/myJSP","name":"cookie02.jsp","lastModified":1642657356364,"locationURI":"file:\/C:\/myJSP\/basicJSP\/src\/main\/webapp\/cookie\/cookie02.jsp"},{"path":"\/basicJSP\/src\/main\/webapp\/request","parentWorkspace":"C:\/myJSP","name":"req_post.jsp","lastModified":1642558534276,"locationURI":"file:\/C:\/myJSP\/basicJSP\/src\/main\/webapp\/request\/req_post.jsp"},{"path":"\/basicJSP\/src\/main\/webapp\/response","parentWorkspace":"C:\/myJSP","name":"res_login_ok.jsp","lastModified":1642645769565,"locationURI":"file:\/C:\/myJSP\/basicJSP\/src\/main\/webapp\/response\/res_login_ok.jsp"},{"path":"\/basicJSP\/src\/main\/webapp\/test","parentWorkspace":"C:\/myJSP","name":"tag_ex01.jsp","lastModified":1642487874995,"locationURI":"file:\/C:\/myJSP\/basicJSP\/src\/main\/webapp\/test\/tag_ex01.jsp"},{"path":"\/basicJSP\/src\/main\/webapp\/test","parentWorkspace":"C:\/myJSP","name":"footer.jsp","lastModified":1642484762332,"locationURI":"file:\/C:\/myJSP\/basicJSP\/src\/main\/webapp\/test\/footer.jsp"},{"path":"\/basicJSP\/src\/main\/webapp\/request","parentWorkspace":"C:\/myJSP","name":"req_get_parameter.jsp","lastModified":1642569348862,"locationURI":"file:\/C:\/myJSP\/basicJSP\/src\/main\/webapp\/request\/req_get_parameter.jsp"},{"path":"\/basicJSP\/src\/main\/webapp\/request","parentWorkspace":"C:\/myJSP","name":"req_get_form.jsp","lastModified":1642569365609,"locationURI":"file:\/C:\/myJSP\/basicJSP\/src\/main\/webapp\/request\/req_get_form.jsp"},{"path":"\/basicJSP\/src\/main\/webapp\/WEB-INF","parentWorkspace":"C:\/myJSP","name":"web.xml","lastModified":1642496060239,"locationURI":"file:\/C:\/myJSP\/basicJSP\/src\/main\/webapp\/WEB-INF\/web.xml"},{"path":"\/basicJSP\/src\/main\/webapp\/session","parentWorkspace":"C:\/myJSP","name":"session_set.jsp","lastModified":1642665412710,"locationURI":"file:\/C:\/myJSP\/basicJSP\/src\/main\/webapp\/session\/session_set.jsp"},{"path":"\/basicJSP\/src\/main\/webapp\/response","parentWorkspace":"C:\/myJSP","name":"login.jsp","lastModified":1642642600064,"locationURI":"file:\/C:\/myJSP\/basicJSP\/src\/main\/webapp\/response\/login.jsp"},{"path":"\/basicJSP\/src\/main\/webapp\/request","parentWorkspace":"C:\/myJSP","name":"req_result.jsp","lastModified":1642559656240,"locationURI":"file:\/C:\/myJSP\/basicJSP\/src\/main\/webapp\/request\/req_result.jsp"},{"path":"\/basicJSP\/src\/main\/webapp\/request","parentWorkspace":"C:\/myJSP","name":"req_quiz_result.jsp","lastModified":1642573451534,"locationURI":"file:\/C:\/myJSP\/basicJSP\/src\/main\/webapp\/request\/req_quiz_result.jsp"},{"path":"\/basicJSP\/src\/main\/webapp\/test","parentWorkspace":"C:\/myJSP","name":"expression.jsp","lastModified":1642478405963,"locationURI":"file:\/C:\/myJSP\/basicJSP\/src\/main\/webapp\/test\/expression.jsp"},{"path":"\/basicJSP\/src\/main\/webapp\/test","parentWorkspace":"C:\/myJSP","name":"section.jsp","lastModified":1642484933578,"locationURI":"file:\/C:\/myJSP\/basicJSP\/src\/main\/webapp\/test\/section.jsp"}]}